[
  {
    "start": "00:05",
    "end": "00:10",
    "text": "崖の村にはそんな大きな魔物が出ているの",
    "audio_file": "clip_000.mp3"
  },
  {
    "start": "00:10",
    "end": "00:16",
    "text": "そうなんです今の僕じゃ追い払うのが精一杯でした",
    "audio_file": "clip_001.mp3"
  },
  {
    "start": "00:16",
    "end": "00:27",
    "text": "武器をもっと強くする方法はないですか / それならロボット山の方で取れる金属で武器を強化できるって聞いたことあるわ",
    "audio_file": "clip_002.mp3"
  },
  {
    "start": "00:28",
    "end": "00:35",
    "text": "山の入り口にある商店でやってくれるはずよ / わかった尋ねてみます",
    "audio_file": "clip_003.mp3"
  },
  {
    "start": "00:35",
    "end": "00:40",
    "text": "教科にはお金が必要だから用意を忘れないでね",
    "audio_file": "clip_004.mp3"
  },
  {
    "start": "00:40",
    "end": "00:43",
    "text": "1000ゴールドくらいだと思うけど",
    "audio_file": "clip_005.mp3"
  },
  {
    "start": "00:48",
    "end": "00:52",
    "text": "ロボット山とはどのようなところなのだ",
    "audio_file": "clip_006.mp3"
  },
  {
    "start": "00:52",
    "end": "01:00",
    "text": "昔の遺跡が埋まっている場所なんだって / 僕たちにはよくわからない鉄屑だらけのところだよ",
    "audio_file": "clip_007.mp3"
  },
  {
    "start": "01:00",
    "end": "01:08",
    "text": "北東の鉄橋を登ったところにあるんだ / あの橋の上を昔は大きな鉄の箱が走ってたんだって",
    "audio_file": "clip_008.mp3"
  },
  {
    "start": "01:08",
    "end": "01:10",
    "text": "ポポルさんが言ってた",
    "audio_file": "clip_009.mp3"
  },
  {
    "start": "01:11",
    "end": "01:15",
    "text": "昔の人間は賢かったようだな",
    "audio_file": "clip_010.mp3"
  },
  {
    "start": "01:15",
    "end": "01:21",
    "text": "本当に賢かったら滅びかけたりはしないと思うけども",
    "audio_file": "clip_011.mp3"
  },
  {
    "start": "01:22",
    "end": "01:26",
    "text": "兄ちゃんお腹すいたよ",
    "audio_file": "clip_012.mp3"
  },
  {
    "start": "01:26",
    "end": "01:30",
    "text": "そっかちょっと待ってろよ",
    "audio_file": "clip_013.mp3"
  },
  {
    "start": "01:30",
    "end": "01:34",
    "text": "確かこっちの棚に",
    "audio_file": "clip_014.mp3"
  },
  {
    "start": "01:42",
    "end": "01:43",
    "text": "こんにちは",
    "audio_file": "clip_015.mp3"
  },
  {
    "start": "01:44",
    "end": "01:51",
    "text": "いらっしゃいます / いらっしゃいってここお店なの?",
    "audio_file": "clip_016.mp3"
  },
  {
    "start": "01:51",
    "end": "01:56",
    "text": "はい / と言っても今はできないんだけど",
    "audio_file": "clip_017.mp3"
  },
  {
    "start": "01:57",
    "end": "02:01",
    "text": "普段は奥にあるロボット山から金属を掘ってきて",
    "audio_file": "clip_018.mp3"
  },
  {
    "start": "02:01",
    "end": "02:05",
    "text": "加工して売ってるんです / ロボット山で?",
    "audio_file": "clip_019.mp3"
  },
  {
    "start": "02:06",
    "end": "02:13",
    "text": "ええ、そうです / 昔は軍事基地だったらしくて / いい素材がたくさんあるんですよ",
    "audio_file": "clip_020.mp3"
  },
  {
    "start": "02:14",
    "end": "02:19",
    "text": "ちょっと危ない場所なんですが / 背に腹は変えられないというか",
    "audio_file": "clip_021.mp3"
  },
  {
    "start": "02:19",
    "end": "02:23",
    "text": "君たち二人だけでやってるの?",
    "audio_file": "clip_022.mp3"
  },
  {
    "start": "02:24",
    "end": "02:28",
    "text": "父さんは弟が幼い頃に死にました",
    "audio_file": "clip_023.mp3"
  },
  {
    "start": "02:29",
    "end": "02:33",
    "text": "母さんは仕入れに出かけてます",
    "audio_file": "clip_024.mp3"
  },
  {
    "start": "02:34",
    "end": "02:37",
    "text": "1,2,3,7つ",
    "audio_file": "clip_025.mp3"
  },
  {
    "start": "02:37",
    "end": "02:41",
    "text": "お母さんもうこれだけ帰ってきてない",
    "audio_file": "clip_026.mp3"
  },
  {
    "start": "02:42",
    "end": "02:47",
    "text": "1週間も? / 最近は奥の方まで行かなきゃ",
    "audio_file": "clip_027.mp3"
  },
  {
    "start": "02:48",
    "end": "02:51",
    "text": "素材が手に入らないらしくて / お兄ちゃん",
    "audio_file": "clip_028.mp3"
  },
  {
    "start": "02:52",
    "end": "02:58",
    "text": "お腹すいたってば / 素材さえあれば武器の加工ができるんだよね",
    "audio_file": "clip_029.mp3"
  },
  {
    "start": "02:59",
    "end": "03:04",
    "text": "ええでも山の中は危険で僕らだけじゃ",
    "audio_file": "clip_030.mp3"
  },
  {
    "start": "03:04",
    "end": "03:08",
    "text": "じゃあ素材は僕が取ってくるよ / え",
    "audio_file": "clip_031.mp3"
  },
  {
    "start": "03:08",
    "end": "03:12",
    "text": "ちょっと僕の武器も強化してもらいたいし",
    "audio_file": "clip_032.mp3"
  },
  {
    "start": "03:12",
    "end": "03:16",
    "text": "それにここで働くには素材がもっと必要でしょ",
    "audio_file": "clip_033.mp3"
  },
  {
    "start": "03:16",
    "end": "03:22",
    "text": "それはそうですが / じゃあ決まりどんな素材が必要",
    "audio_file": "clip_034.mp3"
  },
  {
    "start": "03:22",
    "end": "03:28",
    "text": "その武器でしたらチタン合金が3つ必要ですね",
    "audio_file": "clip_035.mp3"
  },
  {
    "start": "03:28",
    "end": "03:33",
    "text": "ロボット山の中にいる防衛ロボットたちから入手することができます",
    "audio_file": "clip_036.mp3"
  },
  {
    "start": "03:33",
    "end": "03:39",
    "text": "分かった / あとこれロボット山の地図です",
    "audio_file": "clip_037.mp3"
  },
  {
    "start": "03:39",
    "end": "03:46",
    "text": "複雑なんで必要だと思います / 気をつけてくださいね本当に危ないですから",
    "audio_file": "clip_038.mp3"
  },
  {
    "start": "03:49",
    "end": "03:54",
    "text": "明るいな / ここはまだ昔の機械が動いてるんだね",
    "audio_file": "clip_039.mp3"
  },
  {
    "start": "03:55",
    "end": "03:58",
    "text": "僕たちには何が何だかさっぱりだけどね",
    "audio_file": "clip_040.mp3"
  },
  {
    "start": "03:58",
    "end": "04:05",
    "text": "旧世界の廃墟か / それを機械たちが永遠と守っているわけだ",
    "audio_file": "clip_041.mp3"
  },
  {
    "start": "04:05",
    "end": "04:08",
    "text": "珍しい素材を持ってそうだね",
    "audio_file": "clip_042.mp3"
  },
  {
    "start": "04:28",
    "end": "04:32",
    "text": "素材はこのくらいで十分かな",
    "audio_file": "clip_043.mp3"
  },
  {
    "start": "04:36",
    "end": "04:43",
    "text": "依頼されたものを集め終わった後って、一気に依頼主のところまでワープしたくなるんだね。",
    "audio_file": "clip_044.mp3"
  },
  {
    "start": "04:44",
    "end": "04:51",
    "text": "ワープ? / そういう名前の遠くまで一気に飛べる魔法があるって聞いたんだけど。",
    "audio_file": "clip_045.mp3"
  },
  {
    "start": "04:52",
    "end": "04:55",
    "text": "ああ、あれはやめておいたほうがいい。 / どうして?",
    "audio_file": "clip_046.mp3"
  },
  {
    "start": "04:56",
    "end": "05:05",
    "text": "何人もの賢者が試そうとしたが、途中にある障害物に衝突して、みんなひき肉になったからな。",
    "audio_file": "clip_047.mp3"
  },
  {
    "start": "05:06",
    "end": "05:09",
    "text": "これはやめておいたほうがいい。",
    "audio_file": "clip_048.mp3"
  },
  {
    "start": "05:10",
    "end": "05:13",
    "text": "ああ、やめておけ。",
    "audio_file": "clip_049.mp3"
  },
  {
    "start": "05:14",
    "end": "05:20",
    "text": "寂しいんだもん!寂しいんだもん!お母さん!",
    "audio_file": "clip_050.mp3"
  },
  {
    "start": "05:26",
    "end": "05:30",
    "text": "おかえりなさい。 / 素材を取ってきたよ。",
    "audio_file": "clip_051.mp3"
  },
  {
    "start": "05:30",
    "end": "05:35",
    "text": "ありがとうございます。すぐに武器を強化しますね。",
    "audio_file": "clip_052.mp3"
  },
  {
    "start": "05:35",
    "end": "05:40",
    "text": "本当は有料なんですが、特別に今回は無料で結構です。",
    "audio_file": "clip_053.mp3"
  },
  {
    "start": "05:47",
    "end": "05:56",
    "text": "はい、どうぞ。 / これでうちも営業することができます。ありがとうございました。",
    "audio_file": "clip_054.mp3"
  },
  {
    "start": "05:56",
    "end": "05:59",
    "text": "お母さん!",
    "audio_file": "clip_055.mp3"
  },
  {
    "start": "05:59",
    "end": "06:01",
    "text": "どうしたの?",
    "audio_file": "clip_056.mp3"
  },
  {
    "start": "06:02",
    "end": "06:06",
    "text": "お騒がせしてすみません / 弟が",
    "audio_file": "clip_057.mp3"
  },
  {
    "start": "06:06",
    "end": "06:08",
    "text": "母さんを探しに行くって",
    "audio_file": "clip_058.mp3"
  },
  {
    "start": "06:10",
    "end": "06:14",
    "text": "もうちょっと待ってたら / きっと帰ってくるから",
    "audio_file": "clip_059.mp3"
  },
  {
    "start": "06:14",
    "end": "06:19",
    "text": "待てよ / な / 待てない",
    "audio_file": "clip_060.mp3"
  },
  {
    "start": "06:19",
    "end": "06:22",
    "text": "お母さん",
    "audio_file": "clip_061.mp3"
  },
  {
    "start": "06:31",
    "end": "06:35",
    "text": "しろう / 言うな もうわかっておる",
    "audio_file": "clip_062.mp3"
  },
  {
    "start": "06:35",
    "end": "06:39",
    "text": "こやつらの母親を探せばいいのだろう",
    "audio_file": "clip_063.mp3"
  },
  {
    "start": "06:41",
    "end": "06:47",
    "text": "いいですいいです そこまでしてもらったら申し訳なくて",
    "audio_file": "clip_064.mp3"
  },
  {
    "start": "06:47",
    "end": "06:52",
    "text": "そんなの気にしないでいいよ だけど",
    "audio_file": "clip_065.mp3"
  },
  {
    "start": "06:54",
    "end": "06:56",
    "text": "カーソンは",
    "audio_file": "clip_066.mp3"
  },
  {
    "start": "06:57",
    "end": "07:01",
    "text": "いえ、なんでもないです。",
    "audio_file": "clip_067.mp3"
  },
  {
    "start": "07:01",
    "end": "07:07",
    "text": "いつもお母さんは山の奥の方まで入って行っています。",
    "audio_file": "clip_068.mp3"
  },
  {
    "start": "07:07",
    "end": "07:13",
    "text": "エレベーターを使うと思いますから、起動パスコードをお渡ししておきます。",
    "audio_file": "clip_069.mp3"
  },
  {
    "start": "07:18",
    "end": "07:24",
    "text": "さてと、あの兄弟のお母さんはロボット山の奥まで行くって言ってたかな。",
    "audio_file": "clip_070.mp3"
  },
  {
    "start": "07:24",
    "end": "07:34",
    "text": "なぜそこまであの兄弟に堅いでするのだ お母さんがいない寂しさは僕たち兄弟も知っているか",
    "audio_file": "clip_071.mp3"
  },
  {
    "start": "09:32",
    "end": "09:36",
    "text": "お前は本当に信じておるのか",
    "audio_file": "clip_072.mp3"
  },
  {
    "start": "09:37",
    "end": "09:42",
    "text": "あやつらの母親が本当にこんなところまで来られたと",
    "audio_file": "clip_073.mp3"
  },
  {
    "start": "09:45",
    "end": "09:52",
    "text": "一週間以上もたった一人で素材を探し続けていると信じているのか?",
    "audio_file": "clip_074.mp3"
  },
  {
    "start": "09:53",
    "end": "09:57",
    "text": "本当に?",
    "audio_file": "clip_075.mp3"
  },
  {
    "start": "09:58",
    "end": "10:02",
    "text": "我が思うに母親はきっともう…",
    "audio_file": "clip_076.mp3"
  },
  {
    "start": "10:02",
    "end": "10:04",
    "text": "生きてるよ",
    "audio_file": "clip_077.mp3"
  },
  {
    "start": "10:06",
    "end": "10:12",
    "text": "信じなきゃ奇跡だって起きない / 奇跡か",
    "audio_file": "clip_078.mp3"
  },
  {
    "start": "11:08",
    "end": "12:13",
    "text": "第3回目",
    "audio_file": "clip_079.mp3"
  },
  {
    "start": "12:14",
    "end": "12:27",
    "text": "潰されるでないぞ 逃げよ / 分かってる / 周囲にキューハレン 気をつけ",
    "audio_file": "clip_080.mp3"
  },
  {
    "start": "12:28",
    "end": "12:32",
    "text": "奴の影を見据えよう",
    "audio_file": "clip_081.mp3"
  },
  {
    "start": "12:33",
    "end": "12:35",
    "text": "よくぞやった",
    "audio_file": "clip_082.mp3"
  },
  {
    "start": "12:36",
    "end": "12:45",
    "text": "手のかかん機関だ / またなんか違うのが出てきた / 雑魚を移送せれば先はないようだな",
    "audio_file": "clip_083.mp3"
  },
  {
    "start": "13:08",
    "end": "13:23",
    "text": "なんか来たよ",
    "audio_file": "clip_084.mp3"
  },
  {
    "start": "13:24",
    "end": "13:36",
    "text": "残すはあの大頭のみだな",
    "audio_file": "clip_085.mp3"
  },
  {
    "start": "13:37",
    "end": "14:09",
    "text": "この大の爆弾が残っている",
    "audio_file": "clip_086.mp3"
  },
  {
    "start": "14:10",
    "end": "14:15",
    "text": "悪眼に食らえばさすがに効くではある / どこかで聞いたような戦い方だけど",
    "audio_file": "clip_087.mp3"
  },
  {
    "start": "14:16",
    "end": "14:17",
    "text": "わかった",
    "audio_file": "clip_088.mp3"
  },
  {
    "start": "14:18",
    "end": "14:21",
    "text": "機械のなんざいで我に歩かうとは / 危ないよシロ",
    "audio_file": "clip_089.mp3"
  },
  {
    "start": "14:22",
    "end": "14:26",
    "text": "よし聞いてる / 死ぬ中か",
    "audio_file": "clip_090.mp3"
  },
  {
    "start": "14:27",
    "end": "14:35",
    "text": "本当に見たままの弱点なのだな",
    "audio_file": "clip_091.mp3"
  },
  {
    "start": "14:36",
    "end": "14:58",
    "text": "負け",
    "audio_file": "clip_092.mp3"
  },
  {
    "start": "14:59",
    "end": "15:02",
    "text": "ТРЕВОЖНАЯ МУЗЫКА",
    "audio_file": "clip_093.mp3"
  },
  {
    "start": "15:21",
    "end": "15:23",
    "text": "女の人",
    "audio_file": "clip_094.mp3"
  },
  {
    "start": "15:24",
    "end": "15:26",
    "text": "もう死んでる",
    "audio_file": "clip_095.mp3"
  },
  {
    "start": "15:27",
    "end": "15:31",
    "text": "あやつらの母親であろう",
    "audio_file": "clip_096.mp3"
  },
  {
    "start": "15:32",
    "end": "15:34",
    "text": "一人じゃなかったんだ",
    "audio_file": "clip_097.mp3"
  },
  {
    "start": "15:35",
    "end": "15:37",
    "text": "男か",
    "audio_file": "clip_098.mp3"
  },
  {
    "start": "15:38",
    "end": "15:41",
    "text": "大きなカバンに綺麗な洋服",
    "audio_file": "clip_099.mp3"
  },
  {
    "start": "15:42",
    "end": "15:44",
    "text": "お金もある",
    "audio_file": "clip_100.mp3"
  },
  {
    "start": "15:44",
    "end": "15:48",
    "text": "どうしてこんなところにこんなものも",
    "audio_file": "clip_101.mp3"
  },
  {
    "start": "15:48",
    "end": "15:55",
    "text": "子供たちを捨てて / 若い男と逃げるつもりだったようだな",
    "audio_file": "clip_102.mp3"
  },
  {
    "start": "15:55",
    "end": "15:57",
    "text": "そんな",
    "audio_file": "clip_103.mp3"
  },
  {
    "start": "15:58",
    "end": "16:03",
    "text": "奇跡は起こらず / 最悪の真実が待っておったな",
    "audio_file": "clip_104.mp3"
  },
  {
    "start": "16:03",
    "end": "16:07",
    "text": "あやつらには何という",
    "audio_file": "clip_105.mp3"
  },
  {
    "start": "16:20",
    "end": "16:26",
    "text": "これは化粧瓶 / バラの匂い",
    "audio_file": "clip_106.mp3"
  },
  {
    "start": "16:27",
    "end": "16:29",
    "text": "これだけでも届けよう",
    "audio_file": "clip_107.mp3"
  },
  {
    "start": "16:39",
    "end": "16:41",
    "text": "お母さんは?",
    "audio_file": "clip_108.mp3"
  },
  {
    "start": "16:53",
    "end": "16:57",
    "text": "ごめんね / 見つけられなかったんだ",
    "audio_file": "clip_109.mp3"
  },
  {
    "start": "16:58",
    "end": "16:59",
    "text": "そんな",
    "audio_file": "clip_110.mp3"
  },
  {
    "start": "17:02",
    "end": "17:07",
    "text": "どこ探したの?本当に探したの?役立たず",
    "audio_file": "clip_111.mp3"
  },
  {
    "start": "17:08",
    "end": "17:12",
    "text": "ほらせっかく皆さんがお前のために",
    "audio_file": "clip_112.mp3"
  },
  {
    "start": "17:12",
    "end": "17:18",
    "text": "いいんです怒らないであげて / 僕はいつまで待ったらいいの?",
    "audio_file": "clip_113.mp3"
  },
  {
    "start": "17:19",
    "end": "17:21",
    "text": "お母さん",
    "audio_file": "clip_114.mp3"
  },
  {
    "start": "17:28",
    "end": "17:33",
    "text": "母さんは一人で死んでましたか",
    "audio_file": "clip_115.mp3"
  },
  {
    "start": "17:34",
    "end": "17:37",
    "text": "えっと",
    "audio_file": "clip_116.mp3"
  },
  {
    "start": "17:38",
    "end": "17:42",
    "text": "いいんです分かってます",
    "audio_file": "clip_117.mp3"
  },
  {
    "start": "17:43",
    "end": "17:48",
    "text": "教えてください / 母さんは好きな人と死ねたんですか",
    "audio_file": "clip_118.mp3"
  },
  {
    "start": "17:48",
    "end": "17:53",
    "text": "遺体は二つあった",
    "audio_file": "clip_119.mp3"
  },
  {
    "start": "17:54",
    "end": "17:57",
    "text": "よかった / 何",
    "audio_file": "clip_120.mp3"
  },
  {
    "start": "17:58",
    "end": "18:02",
    "text": "母さんはもう俺たちのことでイライラしたり",
    "audio_file": "clip_121.mp3"
  },
  {
    "start": "18:03",
    "end": "18:06",
    "text": "悩まなくて済むんだ / これで",
    "audio_file": "clip_122.mp3"
  },
  {
    "start": "18:07",
    "end": "18:10",
    "text": "よかったと思います",
    "audio_file": "clip_123.mp3"
  },
  {
    "start": "18:10",
    "end": "18:12",
    "text": "許せるの",
    "audio_file": "clip_124.mp3"
  },
  {
    "start": "18:14",
    "end": "18:18",
    "text": "俺は母さんの子供だから",
    "audio_file": "clip_125.mp3"
  },
  {
    "start": "18:18",
    "end": "18:21",
    "text": "俺の母さんはあの人だけだから",
    "audio_file": "clip_126.mp3"
  },
  {
    "start": "18:22",
    "end": "18:23",
    "text": "だから",
    "audio_file": "clip_127.mp3"
  },
  {
    "start": "18:24",
    "end": "18:25",
    "text": "この瓶",
    "audio_file": "clip_128.mp3"
  },
  {
    "start": "18:26",
    "end": "18:28",
    "text": "拾ってきたんだけど",
    "audio_file": "clip_129.mp3"
  },
  {
    "start": "18:34",
    "end": "18:35",
    "text": "これは",
    "audio_file": "clip_130.mp3"
  },
  {
    "start": "18:37",
    "end": "18:42",
    "text": "母さんの香水だ / 母さんの",
    "audio_file": "clip_131.mp3"
  },
  {
    "start": "18:43",
    "end": "18:44",
    "text": "匂いだ",
    "audio_file": "clip_132.mp3"
  },
  {
    "start": "18:46",
    "end": "18:50",
    "text": "こんなの / なんで涙が出るんだ",
    "audio_file": "clip_133.mp3"
  },
  {
    "start": "18:51",
    "end": "18:55",
    "text": "泣いちゃダメだ / こんなところ",
    "audio_file": "clip_134.mp3"
  },
  {
    "start": "18:56",
    "end": "18:57",
    "text": "弟に見られたら",
    "audio_file": "clip_135.mp3"
  },
  {
    "start": "18:58",
    "end": "19:24",
    "text": "くそ / くそ",
    "audio_file": "clip_136.mp3"
  },
  {
    "start": "19:25",
    "end": "19:30",
    "text": "これで良かったのかな",
    "audio_file": "clip_137.mp3"
  },
  {
    "start": "19:31",
    "end": "19:34",
    "text": "ありがとうございました / 本当に",
    "audio_file": "clip_138.mp3"
  },
  {
    "start": "19:35",
    "end": "19:39",
    "text": "いろいろありがとうございました",
    "audio_file": "clip_139.mp3"
  },
  {
    "start": "19:40",
    "end": "19:43",
    "text": "これでよかったのだ / きっと",
    "audio_file": "clip_140.mp3"
  }
]