[
  {
    "start": "16:51",
    "end": "17:02",
    "text": "シンジ君に何も言う資格ない / もういい / その上こうやって / 都合のいい時だけ男にすがろうとする / ずるい女なのよ / あの時だってカジ君を利用してただけかもしれない / やんなるわ",
    "audio_file": "clip_108.mp3",
    "translation": "I have no right to say anything to Shinji. Enough already. On top of that, I try to cling to men only when it's convenient. I'm such a cunning woman. Back then, I might have just been using Kaji. I'm disgusted with myself.",
    "vocabulary": [
      {"word": "資格", "reading": "しかく", "meaning": "qualification, right"},
      {"word": "都合", "reading": "つごう", "meaning": "convenience, circumstances"},
      {"word": "すがる", "reading": "すがる", "meaning": "to cling to, to depend on"},
      {"word": "ずるい", "reading": "ずるい", "meaning": "cunning, sly, unfair"},
      {"word": "利用する", "reading": "りようする", "meaning": "to use, to make use of"}
    ],
    "grammar": "すがろうとする uses volitional form + とする to express 'trying to do something'"
  },
  {
    "start": "17:03",
    "end": "17:09",
    "text": "もういいやめろ / 自分に絶望するわよ / ああああああ",
    "audio_file": "clip_109.mp3",
    "translation": "That's enough, stop it. I'll end up despairing of myself. Ahhhh.",
    "vocabulary": [
      {"word": "絶望", "reading": "ぜつぼう", "meaning": "despair, hopelessness"},
      {"word": "やめろ", "reading": "やめろ", "meaning": "stop it (imperative form of やめる)"}
    ],
    "grammar": "絶望する - the verb form of the noun 絶望, meaning 'to despair' or 'to lose hope'"
  },
  {
    "start": "17:29",
    "end": "17:43",
    "text": "ねえシンジー キスしようか / ん? 何? / キスよ、キス。したことないでしょ? / うん。 / じゃあ、しよう。 / どうして? / 退屈だからよ。",
    "audio_file": "clip_110.mp3",
    "translation": "Hey Shinji, shall we kiss? Hm? What? A kiss, a kiss. You've never done it, have you? Yeah. Then let's do it. Why? Because I'm bored.",
    "vocabulary": [
      {"word": "キス", "reading": "キス", "meaning": "kiss"},
      {"word": "退屈", "reading": "たいくつ", "meaning": "boredom, tedium"},
      {"word": "したことない", "reading": "したことない", "meaning": "have never done"}
    ],
    "grammar": "しようか is volitional form + か, used to suggest or propose doing something together"
  },
  {
    "start": "17:43",
    "end": "17:49",
    "text": "退屈だからって、そんな。 / お母さんの命日に女の子とキスするの嫌?",
    "audio_file": "clip_111.mp3",
    "translation": "Just because you're bored, that's... Do you hate kissing a girl on your mother's death anniversary?",
    "vocabulary": [
      {"word": "命日", "reading": "めいにち", "meaning": "death anniversary"},
      {"word": "嫌", "reading": "いや", "meaning": "unpleasant, disagreeable, hate"}
    ],
    "grammar": "だからって is a casual contraction of だからといって, meaning 'just because'"
  },
  {
    "start": "17:49",
    "end": "18:01",
    "text": "天国から見てるかもしれないからって。 / 別に。 / それとも怖い? / 怖くないよ、キスくらい。 / はっ、磨いてるわよね。 / うん。 / じゃあ、行くわよ。",
    "audio_file": "clip_112.mp3",
    "translation": "Because she might be watching from heaven, you mean? Not really. Or are you scared? I'm not scared of something like a kiss. Ha, you do brush your teeth, right? Yeah. Okay, here I go.",
    "vocabulary": [
      {"word": "天国", "reading": "てんごく", "meaning": "heaven, paradise"},
      {"word": "怖い", "reading": "こわい", "meaning": "scary, afraid"},
      {"word": "磨く", "reading": "みがく", "meaning": "to brush, to polish"}
    ],
    "grammar": "くらい after a noun minimizes its importance - 'something as trivial as a kiss'"
  },
  {
    "start": "18:09",
    "end": "18:13",
    "text": "鼻息がこそばゆいから息しないで",
    "audio_file": "clip_113.mp3",
    "translation": "Your breath through your nose is ticklish, so don't breathe.",
    "vocabulary": [
      {"word": "鼻息", "reading": "はないき", "meaning": "nasal breathing, breath through nose"},
      {"word": "こそばゆい", "reading": "こそばゆい", "meaning": "ticklish"},
      {"word": "息", "reading": "いき", "meaning": "breath"}
    ],
    "grammar": "しないで is the negative te-form, used here as a soft command meaning 'don't do'"
  },
  {
    "start": "18:29",
    "end": "18:32",
    "text": "あっ?",
    "audio_file": "clip_114.mp3",
    "translation": "Huh?",
    "vocabulary": [
      {"word": "あっ", "reading": "あっ", "meaning": "exclamation of surprise"}
    ],
    "grammar": "Simple interjection expressing surprise or realization"
  },
  {
    "start": "18:56",
    "end": "19:02",
    "text": "うえぇ、やっぱ暇つぶしにやるもんじゃないわ",
    "audio_file": "clip_115.mp3",
    "translation": "Ugh, kissing really isn't something you should do just to kill time.",
    "vocabulary": [
      {"word": "暇つぶし", "reading": "ひまつぶし", "meaning": "killing time, pastime"},
      {"word": "やっぱ", "reading": "やっぱ", "meaning": "as expected, after all (casual)"}
    ],
    "grammar": "もんじゃない is casual form of ものではない, expressing 'should not do' or 'not something one does'"
  },
  {
    "start": "19:04",
    "end": "19:08",
    "text": "ほら、着いたぞ、しっかりしろ",
    "audio_file": "clip_116.mp3",
    "translation": "Hey, we've arrived. Pull yourself together.",
    "vocabulary": [
      {"word": "着く", "reading": "つく", "meaning": "to arrive"},
      {"word": "しっかりする", "reading": "しっかりする", "meaning": "to pull oneself together, to be firm"}
    ],
    "grammar": "しろ is the imperative form of する, giving a direct command"
  },
  {
    "start": "19:09",
    "end": "19:12",
    "text": "カジさん",
    "audio_file": "clip_117.mp3",
    "translation": "Kaji-san...",
    "vocabulary": [
      {"word": "さん", "reading": "さん", "meaning": "honorific suffix"}
    ],
    "grammar": "Simple address using the polite suffix さん"
  },
  {
    "start": "19:12",
    "end": "19:15",
    "text": "カジさん",
    "audio_file": "clip_118.mp3",
    "translation": "Kaji-san...",
    "vocabulary": [
      {"word": "さん", "reading": "さん", "meaning": "honorific suffix"}
    ],
    "grammar": "Repeated address showing emotional attachment or neediness"
  },
  {
    "start": "19:16",
    "end": "19:22",
    "text": "じゃあ、俺は帰るから / カジさんも泊まっていけば?",
    "audio_file": "clip_119.mp3",
    "translation": "Well, I'm heading home. / Why don't you stay over too, Kaji-san?",
    "vocabulary": [
      {"word": "帰る", "reading": "かえる", "meaning": "to return home"},
      {"word": "泊まる", "reading": "とまる", "meaning": "to stay overnight"}
    ],
    "grammar": "ていけば is te-form + いく in conditional form, suggesting 'why don't you (do and go/continue)'"
  },
  {
    "start": "19:22",
    "end": "19:32",
    "text": "この格好で出勤したら笑われちゃうよ / ええ?大丈夫よ。ねええ。カジさんてば。 / またな。",
    "audio_file": "clip_120.mp3",
    "translation": "If I went to work dressed like this, I'd be laughed at. / Huh? It's fine. Hey. Kaji-san, come on. / See you.",
    "vocabulary": [
      {"word": "格好", "reading": "かっこう", "meaning": "appearance, outfit"},
      {"word": "出勤", "reading": "しゅっきん", "meaning": "going to work"},
      {"word": "笑われる", "reading": "わらわれる", "meaning": "to be laughed at (passive)"}
    ],
    "grammar": "てば is a casual suffix used to get someone's attention or express mild frustration"
  },
  {
    "start": "19:35",
    "end": "19:46",
    "text": "ラベンダーの香りがする。 / すまないが、二人ともカツラギのこと頼んだぞ。 / はい。 / じゃあ、おやすみ。 / おやすみなさい。",
    "audio_file": "clip_121.mp3",
    "translation": "There's a lavender scent. / Sorry, but I'm counting on you two to take care of Katsuragi. / Yes. / Well, goodnight. / Goodnight.",
    "vocabulary": [
      {"word": "香り", "reading": "かおり", "meaning": "scent, fragrance"},
      {"word": "頼む", "reading": "たのむ", "meaning": "to request, to count on"}
    ],
    "grammar": "頼んだぞ uses past tense + ぞ for emphatic request - 'I'm counting on you'"
  },
  {
    "start": "19:47",
    "end": "19:53",
    "text": "どうしたの?元きないね。 / あんたなんかとキスしたからよ!",
    "audio_file": "clip_122.mp3",
    "translation": "What's wrong? You seem down. / It's because I kissed someone like you!",
    "vocabulary": [
      {"word": "元気", "reading": "げんき", "meaning": "energy, vigor, well-being"},
      {"word": "なんか", "reading": "なんか", "meaning": "something like, the likes of (dismissive)"}
    ],
    "grammar": "なんか after a person is dismissive/derogatory - 'someone like you' (in a negative way)"
  },
  {
    "start": "19:53",
    "end": "19:58",
    "text": "では続いて女子綾波",
    "audio_file": "clip_123.mp3",
    "translation": "Next, for the girls, Ayanami.",
    "vocabulary": [
      {"word": "続いて", "reading": "つづいて", "meaning": "next, following"},
      {"word": "女子", "reading": "じょし", "meaning": "girl, female"}
    ],
    "grammar": "続いて is the te-form of 続く used adverbially to mean 'following' or 'next'"
  },
  {
    "start": "19:58",
    "end": "20:03",
    "text": "綾波は今日も休みか / Пс-с-с.",
    "audio_file": "clip_124.mp3",
    "translation": "Ayanami is absent again today, huh. / Psst.",
    "vocabulary": [
      {"word": "休み", "reading": "やすみ", "meaning": "absence, day off, rest"},
      {"word": "今日も", "reading": "きょうも", "meaning": "today too, again today"}
    ],
    "grammar": "か at the end of a statement indicates rhetorical confirmation or mild surprise"
  },
  {
    "start": "20:42",
    "end": "20:53",
    "text": "2日酔いの調子はどうだ? / おかげでやっと冷めたわ / そりゃよかった / これがあなたの本当の仕事? / それともアルバイトかしら? / どっちかな?",
    "audio_file": "clip_125.mp3",
    "translation": "How's the hangover? / Thanks to that, I've finally sobered up. / That's good. / Is this your real job? Or is it a side job? / Which one, I wonder?",
    "vocabulary": [
      {"word": "二日酔い", "reading": "ふつかよい", "meaning": "hangover"},
      {"word": "冷める", "reading": "さめる", "meaning": "to cool down, to sober up"},
      {"word": "アルバイト", "reading": "アルバイト", "meaning": "part-time job, side job"}
    ],
    "grammar": "おかげで expresses 'thanks to' something, often used both sincerely and sarcastically"
  },
  {
    "start": "20:53",
    "end": "21:03",
    "text": "特務機関NERV特殊監査部所属カジ領事 / 同時に日本政府内務省調査部所属カジ領事でもあるわけね / バレバレか? / ネルフは甘く見ないで",
    "audio_file": "clip_126.mp3",
    "translation": "Kaji Ryoji, belonging to NERV Special Agency's Special Inspection Division. At the same time, you're also Kaji Ryoji belonging to the Japanese Government's Ministry of Internal Affairs Investigation Division, right? / Was it that obvious? / Don't underestimate NERV.",
    "vocabulary": [
      {"word": "特務機関", "reading": "とくむきかん", "meaning": "special agency"},
      {"word": "所属", "reading": "しょぞく", "meaning": "belonging to, affiliation"},
      {"word": "バレバレ", "reading": "バレバレ", "meaning": "completely obvious, totally exposed"},
      {"word": "甘く見る", "reading": "あまくみる", "meaning": "to underestimate"}
    ],
    "grammar": "わけね uses わけ (reason/explanation) + ね for confirmation - 'so that's how it is, right?'"
  },
  {
    "start": "21:04",
    "end": "21:11",
    "text": "イカリ司令の命令か? / 私の独断よ / これ以上バイトを続けると / 死ぬわ",
    "audio_file": "clip_127.mp3",
    "translation": "Is this Commander Ikari's order? / It's my own decision. / If you continue this side job any further, you'll die.",
    "vocabulary": [
      {"word": "命令", "reading": "めいれい", "meaning": "order, command"},
      {"word": "独断", "reading": "どくだん", "meaning": "one's own judgment, arbitrary decision"},
      {"word": "続ける", "reading": "つづける", "meaning": "to continue"}
    ],
    "grammar": "これ以上...と means 'if (you do) any more than this' - expressing a warning about consequences"
  },
  {
    "start": "21:11",
    "end": "21:15",
    "text": "イカリ司令は俺を利用してる / まだ行けるさ",
    "audio_file": "clip_128.mp3",
    "translation": "Commander Ikari is using me. / I can still keep going.",
    "vocabulary": [
      {"word": "利用する", "reading": "りようする", "meaning": "to use, to make use of"},
      {"word": "行ける", "reading": "いける", "meaning": "can go, can manage"}
    ],
    "grammar": "さ at the end adds casual assertion or reassurance to the statement"
  },
  {
    "start": "21:15",
    "end": "21:23",
    "text": "だけどカツラゲに隠し事をしてたのは謝るよ / 昨日のお礼にチャラにするわ / それはどう思う / ただ",
    "audio_file": "clip_129.mp3",
    "translation": "But I do apologize for keeping secrets from you, Katsuragi. / I'll call it even as thanks for last night. / What do you think about that? / However...",
    "vocabulary": [
      {"word": "隠し事", "reading": "かくしごと", "meaning": "secret, something hidden"},
      {"word": "謝る", "reading": "あやまる", "meaning": "to apologize"},
      {"word": "チャラ", "reading": "チャラ", "meaning": "even, quits, cancelled out"}
    ],
    "grammar": "チャラにする means 'to call it even' or 'to cancel out' - colloquial expression"
  },
  {
    "start": "21:23",
    "end": "21:29",
    "text": "司令やリッチャンも君に隠し事をしてる / それがこれさ",
    "audio_file": "clip_130.mp3",
    "translation": "The Commander and Ritsuko are also keeping secrets from you. / This is what it is.",
    "vocabulary": [
      {"word": "司令", "reading": "しれい", "meaning": "commander"},
      {"word": "隠し事", "reading": "かくしごと", "meaning": "secret"}
    ],
    "grammar": "や is used to list items non-exhaustively, implying there may be others"
  },
  {
    "start": "21:33",
    "end": "21:36",
    "text": "これは…",
    "audio_file": "clip_131.mp3",
    "translation": "This is...",
    "vocabulary": [
      {"word": "これ", "reading": "これ", "meaning": "this"}
    ],
    "grammar": "Trailing off with は... indicates shock or inability to complete the thought"
  },
  {
    "start": "21:37",
    "end": "21:48",
    "text": "エヴァ… / いえ… / マサク… / そう…セカンドインパクトからそのすべての要であり / 始まりでもある",
    "audio_file": "clip_132.mp3",
    "translation": "Eva... / No... / Could it be... / Yes... The keystone of everything since Second Impact, and also the beginning.",
    "vocabulary": [
      {"word": "要", "reading": "かなめ", "meaning": "keystone, pivot, essential point"},
      {"word": "始まり", "reading": "はじまり", "meaning": "beginning, start"}
    ],
    "grammar": "であり...でもある uses formal copula forms to link two descriptions of the same thing"
  },
  {
    "start": "21:48",
    "end": "21:59",
    "text": "アダムだ / アダム…あの第一使徒がここに… / 確かに ネルフは私が考えているほど甘くないわね",
    "audio_file": "clip_133.mp3",
    "translation": "It's Adam. / Adam... The First Angel is here... / Indeed, NERV isn't as naive as I thought.",
    "vocabulary": [
      {"word": "使徒", "reading": "しと", "meaning": "apostle, angel (in Eva context)"},
      {"word": "確かに", "reading": "たしかに", "meaning": "certainly, indeed"},
      {"word": "甘い", "reading": "あまい", "meaning": "naive, soft, lenient"}
    ],
    "grammar": "ほど甘くない - 'not as ~ as' structure using ほど for comparison"
  },
  {
    "start": "23:19",
    "end": "23:24",
    "text": "ご / 視聴ありがとうございました",
    "audio_file": "clip_134.mp3",
    "translation": "Thank you for watching.",
    "vocabulary": [
      {"word": "視聴", "reading": "しちょう", "meaning": "viewing, watching"},
      {"word": "ありがとうございました", "reading": "ありがとうございました", "meaning": "thank you (past/completed)"}
    ],
    "grammar": "ございました is the polite past form, used in formal expressions of gratitude"
  }
]
